[
  {
    "name": "Normal Menu",
    "checks": [],
    "subChecklists": [
      {
        "name": "Preflight",
        "checks": [
          {
            "name": "Inspections and security",
            "expectedValue": "Completed",
            "isAutomatic": false
          },
          {
            "name": "Oxygen",
            "expectedValue": "Tested, 100%",
            "isAutomatic": false
          },
          {
            "name": "Flight instruments",
            "expectedValue": "Heading___, Altimeter___",
            "isAutomatic": false
          },
          {
            "name": "Parking brake",
            "expectedValue": "Set",
            "isAutomatic": true
          },
          {
            "name": "Fuel control switches",
            "expectedValue": "CUTOFF",
            "isAutomatic": true
          },
          {
            "name": "Taxi and takeoff briefing",
            "expectedValue": "Completed",
            "isAutomatic": false
          },
          {
            "name": "PFD",
            "expectedValue": "V2___, LNAV/VNAV__, ALTITUDE__",
            "isAutomatic": false
          },
          {
            "name": "Takeoff speeds",
            "expectedValue": "V1___, VR___, V2___",
            "isAutomatic": false
          },
          {
            "name": "CDU preflight",
            "expectedValue": "Completed",
            "isAutomatic": false
          }
        ]
      },
      {
        "name": "Before Start",
        "checks": [
          {
            "name": "Flight deck door",
            "expectedValue": "Closed and locked",
            "isAutomatic": false
          },
          {
            "name": "Passenger signs",
            "expectedValue": "__",
            "isAutomatic": false
          },
          {
            "name": "Beacon",
            "expectedValue": "ON",
            "isAutomatic": true
          },
          {
            "name": "Trasponder",
            "expectedValue": "XPNDR",
            "isAutomatic": true
          }
        ]
      },
      {
        "name": "Before Taxi",
        "checks": [
          {
            "name": "Anti-ice",
            "expectedValue": "___",
            "isAutomatic": false
          },
          {
            "name": "Recall",
            "expectedValue": "Checked",
            "isAutomatic": false
          },
          {
            "name": "Autobrake",
            "expectedValue": "RTO",
            "isAutomatic": true
          },
          {
            "name": "Flaps",
            "expectedValue": "___",
            "isAutomatic": true
          },
          {
            "name": "Ground crew clearance",
            "expectedValue": "Seen",
            "isAutomatic": false
          },
          {
            "name": "Flight controls",
            "expectedValue": "Checked",
            "isAutomatic": false
          }
        ]
      },
      {
        "name": "Before Takeoff",
        "checks": [
          {
            "name": "Final Loadsheet / Time ___z",
            "expectedValue": "Acknowledged",
            "isAutomatic": false
          },
          {
            "name": "Critical data changes",
            "expectedValue": "",
            "isAutomatic": false,
            "conditionalChecksYes": [
              "Takeoff briefing",
              "Flaps",
              "Trim"
            ],
            "conditionalChecksNo": []
          },
          {
            "name": "Takeoff briefing",
            "expectedValue": "Updated",
            "isAutomatic": false
          },
          {
            "name": "Flaps",
            "expectedValue": "___",
            "isAutomatic": true
          },
          {
            "name": "Trim",
            "expectedValue": "__ Units, 0, 0",
            "isAutomatic": false
          },
          {
            "name": "Cabin report",
            "expectedValue": "Received",
            "isAutomatic": false
          },
          {
            "name": "Transponder",
            "expectedValue": "TA/RA",
            "isAutomatic": true
          }
        ]
      },
      {
        "name": "After Takeoff",
        "checks": [
          {
            "name": "Landing gear",
            "expectedValue": "UP",
            "isAutomatic": false
          },
          {
            "name": "Flaps",
            "expectedValue": "UP",
            "isAutomatic": false
          },
          {
            "name": "Altimeters",
            "expectedValue": "STD",
            "isAutomatic": false
          }
        ]
      },
      {
        "name": "Descent",
        "checks": [
          {
            "name": "Recall",
            "expectedValue": "Checked",
            "isAutomatic": false
          },
          {
            "name": "Notes",
            "expectedValue": "Checked",
            "isAutomatic": false
          },
          {
            "name": "Autobrake",
            "expectedValue": "___",
            "isAutomatic": false
          },
          {
            "name": "Landing data",
            "expectedValue": "VREF__, Minimums__",
            "isAutomatic": false
          },
          {
            "name": "Approach briefing",
            "expectedValue": "Completed",
            "isAutomatic": false
          }
        ]
      },
      {
        "name": "Approach",
        "checks": [
          {
            "name": "Altimeters",
            "expectedValue": "__",
            "isAutomatic": false
          }
        ]
      },
      {
        "name": "Landing",
        "checks": [
          {
            "name": "Cabin report",
            "expectedValue": "Received",
            "isAutomatic": false
          },
          {
            "name": "Speedbrake",
            "expectedValue": "ARMED",
            "isAutomatic": true
          },
          {
            "name": "Landing gear",
            "expectedValue": "DOWN",
            "isAutomatic": true
          },
          {
            "name": "Flaps",
            "expectedValue": "___",
            "isAutomatic": true
          }
        ]
      },
      {
        "name": "After landing",
        "checks": [
          {
            "name": "Speedbrake",
            "expectedValue": "DOWN",
            "isAutomatic": true
          },
          {
            "name": "strobe and landing lights",
            "expectedValue": "OFF",
            "isAutomatic": true
          },
          {
            "name": "Weather radar",
            "expectedValue": "Off",
            "isAutomatic": true
          },
          {
            "name": "Flaps",
            "expectedValue": "UP",
            "isAutomatic": true
          },
          {
            "name": "Transponder",
            "expectedValue": "XPNDR",
            "isAutomatic": true
          },
          {
            "name": "NOTE",
            "expectedValue": "Carry out Engine Out Taxi In unless there are overriding safety or operational considerations",
            "isAutomatic": true
          }
        ]
      },
      {
        "name": "Shutdown",
        "checks": [
          {
            "name": "Parking brake",
            "expectedValue": "Set",
            "isAutomatic": true
          },
          {
            "name": "Fuel control switches",
            "expectedValue": "CUTOFF",
            "isAutomatic": true
          },
          {
            "name": "Doors",
            "expectedValue": "Manual",
            "isAutomatic": true
          },
          {
            "name": "Seat belt signs",
            "expectedValue": "OFF",
            "isAutomatic": true
          },
          {
            "name": "Hydraulic panel",
            "expectedValue": "Set",
            "isAutomatic": true
          },
          {
            "name": "Fuel pumps",
            "expectedValue": "Off",
            "isAutomatic": true
          },
          {
            "name": "Beacon",
            "expectedValue": "Off",
            "isAutomatic": true
          },
          {
            "name": "Transponder",
            "expectedValue": "2000, STBY",
            "isAutomatic": true
          }
        ]
      },
      {
        "name": "Secure",
        "checks": [
          {
            "name": "ADIRU",
            "expectedValue": "OFF",
            "isAutomatic": true
          },
          {
            "name": "Emergency lights",
            "expectedValue": "OFF",
            "isAutomatic": true
          },
          {
            "name": "Packs",
            "expectedValue": "OFF",
            "isAutomatic": true
          },
          {
            "name": "PCA available",
            "expectedValue": "",
            "isAutomatic": false
          },
          {
            "name": "EXT PWR",
            "expectedValue": "ON",
            "isAutomatic": true
          },
          {
            "name": "APU",
            "expectedValue": "OFF",
            "isAutomatic": true
          },
          {
            "name": "Battery",
            "expectedValue": "OFF",
            "isAutomatic": true
          },
          {
            "name": "F/D access switch",
            "expectedValue": "Unlocked",
            "isAutomatic": false
          }
        ]
      }
    ]
  },
  {
    "name": "Resets",
    "checks": [],
    "subChecklists": [
      {
        "name": "Reset normal"
      },
      {
        "name": "Reset non-normal"
      },
      {
        "name": "Reset all"
      }
    ]
  },
  {
    "name": "Non-normal Menu",
    "checks": [],
    "subChecklists": [
      {
        "name": "Unannunciated checklists",
        "subChecklists": [
          {
            "name": "Engine ...",
            "checks": [],
            "subChecklists": [
              {
                "name": "Aborted engine start L",
                "checks": [
                  {
                    "name":"Condition", 
                    "expectedValue":"On the ground, an aborted left engine start is needed.",
                    "isAutomatic": true
                  },
                  {
                    "name": "L FUEL CONTROL switch",
                    "expectedValue": "CUTOFF",
                    "isAutomatic": true
                  },
                  {
                    "name": "L START selector",
                    "expectedValue": "START",
                    "isAutomatic": false
                  },
                  {
                    "name": "Motor the engine for 30 seconds.",
                    "expectedValue": "",
                    "isAutomatic": false
                  },
                  {
                    "name": "L START selector",
                    "expectedValue": "NORM",
                    "isAutomatic": true
                  }
                ],
                "subChecklists": []
              },
              {
                "name": "Aborted engine start R",
                "checks": [
                  {
                    "name":"Condition", 
                    "expectedValue":"On the ground, an aborted right engine start is needed.",
                    "isAutomatic": true
                  },
                  {
                    "name":"R FUEL CONTROL switch", 
                    "expectedValue":"CUTOFF",
                    "isAutomatic": true
                  },
                  {
                    "name":"R START selector", 
                    "expectedValue":"START",
                    "isAutomatic": false
                  },
                  {
                    "name":"Motor the engine for 30 seconds", 
                    "expectedValue":"",
                    "isAutomatic": false
                  },
                  {
                    "name":"R START selector", 
                    "expectedValue":"NORM",
                    "isAutomatic": true
                  }

                ],
                "subChecklists": []
              },
              {
                "name": "Dual eng fail/stall",
                "checks": [
                  {
                    "name":"Condition", 
                    "expectedValue":"Engine speed for both engines is below idle",
                    "isAutomatic": true
                  },
                  {
                    "name":"FUEL CONTROL switches (both)", 
                    "expectedValue":"CUTOFF, then RUN",
                    "isAutomatic": false
                  },
                  {
                    "name":"RAM AIR TURBINE switch", 
                    "expectedValue":"Push and hold for 1 second",
                    "isAutomatic": true
                  },
                  {
                    "name":"Do not manually abort the start of EGT turns red. EGT turns red when EGT exceeds the start limit line (lower red line). Autostart discontinues the current start attempt before EGT becomes too high for continued engine operation.", 
                    "expectedValue":"",
                    "isAutomatic": false
                  },
                  {
                    "name":"Set airspeed above 270 knots", 
                    "expectedValue":"",
                    "isAutomatic": false
                  },
                  {
                    "name":"APU selector (if APU available)", 
                    "expectedValue":"START, then ON",
                    "isAutomatic": true
                  },
                  {
                    "name":"Engines can accelerate to idle very slowly, especially at high altitutes. The time from fuel control switch to RUN to stabilized idle can take up to two and a half minutes.", 
                    "expectedValue":"",
                    "isAutomatic": false
                  },
                  {
                    "name":"Do not interrupt autostart. Move the fuel control switch to CUTOFF only when no further start attempts are needed.", 
                    "expectedValue":"",
                    "isAutomatic": true
                  },
                  {
                    "name":"Fuel CENTER PUPMS switches (both)", 
                    "expectedValue":"off",
                    "isAutomatic": false
                  },
                  {
                    "name":"Fuel CENTER PUMPS switches (both)", 
                    "expectedValue":"ON",
                    "isAutomatic": true
                  },
                  {
                    "name":"When the HEAT PILOT L+C+R message blanks: ", 
                    "expectedValue":"",
                    "isAutomatic": false
                  },
                  {
                    "name":"PRIMARY FLIGHT COMPUTERS disconnect switch", 
                    "expectedValue":"DISC, then AUTO",
                    "isAutomatic": true
                  },
                  {
                    "name":"NOTE", 
                    "expectedValue":"This step restores the flight control normal mode",
                    "isAutomatic": true
                  },
                  {
                    "name":"Re-engage the autopilot as needed when the flight control normal mode is restored", 
                    "expectedValue":"",
                    "isAutomatic": true
                  }
                ],
                "subChecklists": []
              },
              {
                "name": "Eng in-flight start L",
                "checks": [
                  {
                    "name":"Condition",
                    "expectedValue":"A left engine is needed and all of the following are true:\n- There is N1 rotation\n- There was no engine fire\n- There is no abnormal airframe vibration",
                    "isAutomatic": true
                  },
                  {
                    "name":"",
                    "expectedValue":"Engine can accelerate to idle very slowly, especially at hight altitudes. The time from fuel control switch to RUN to stabilized idle can take up to two and a half minutes.",
                    "isAutomatic": false
                  },
                  {
                    "name":"If N2 is steadily increasing and EGT stays within limits, do not interrupt the start",
                    "expectedValue":"",
                    "isAutomatic": true
                  },
                  {
                    "name":"Crossbleed indication (X-BLD or XB) shows:",
                    "expectedValue":"",
                    "isAutomatic": false,
                    "conditionalChecksYes": [
                      "L START selector"
                    ],
                    "conditionalChecksNo": []
                  },
                  {
                    "name":"L START selector",
                    "expectedValue":"START",
                    "isAutomatic": false
                  },
                  {
                    "name":"Autostart is on:",
                    "expectedValue":"",
                    "isAutomatic": false,
                    "conditionalChecksYes": [
                      "Monitor EGT during start to prevent an EGT exceedance. Autostart allows EGT to exceed the in-flight start limit.",
                      "Do not interrupt autostart. Only abort the start if: .....",
                      "L FUEL CONTROL switch"
                    ],
                    "conditionalChecksNo": ["Abort the start if: .....",
                      "Crossbleed indication (X-BLD or XB) shows:"]
                  },
                  {
                    "name":"Monitor EGT during start to prevent an EGT exceedance. Autostart allows EGT to exceed the in-flight start limit.",
                    "expectedValue":"",
                    "isAutomatic": false
                  },
                  {
                    "name":"Do not interrupt autostart. Only abort the start if: .....",
                    "expectedValue":"",
                    "isAutomatic": false
                  },
                  {
                    "name":"L FUEL CONTROL switch",
                    "expectedValue":"RUN",
                    "isAutomatic": false
                  },
                  {
                    "name":"Abort the start if: .....",
                    "expectedValue":"",
                    "isAutomatic": false
                  },
                  {
                    "name":"Crossbleed indication (X-BLD or XB) shows:",
                    "expectedValue":"",
                    "isAutomatic": false,
                    "conditionalCheckYes": ["L FUEL CONTROL switch"],
                    "conditionalCheckNo": []
                  },
                  {
                    "name":"L FUEL CONTROL switch",
                    "expectedValue":"RUN",
                    "isAutomatic": false
                  },
                  {
                    "name":"Engine starts and runs normally:",
                    "expectedValue":"",
                    "isAutomatic": false,
                    "conditionalCheckYes": ["GND PROX FLAP OVRD switch","Transponder mode selector"],
                    "conditionalCheckNo": []
                  },
                  {
                    "name":"GND PROX FLAP OVRD switch",
                    "expectedValue":"Off",
                    "isAutomatic": true
                  },
                  {
                    "name":"Transponder mode selector",
                    "expectedValue":"TA/RA",
                    "isAutomatic": true
                  },
                  {
                    "name":"L FUEL CONTROL switch",
                    "expectedValue":"Confirm......CUTOFF",
                    "isAutomatic": true
                  },
                  {
                    "name":"L START selector",
                    "expectedValue":"NORM",
                    "isAutomatic": true
                  },
                  {
                    "name":"Plan to land at the nearest suitable airport",
                    "expectedValue":"",
                    "isAutomatic": false
                  },
                  {
                    "name":"NOTE",
                    "expectedValue":"Check the Non-Normal Configuration Landing Distance tables for END SHUTDOWN L, R in the Performance Inflight-QRH chapter or other approved source.",
                    "isAutomatic": true
                  }
                ],
                "subChecklists": []
              },
              {
                "name": "Eng in-flight start R",
                "checks": [

                  
                ],
                "subChecklists": []
              },
              {
                "name": "Eng lim/surge/stall L",
                "checks": [
                  {
                    "name":"Condition",
                    "expectedValue":"",
                    "isAutomatic": true
                  }
                ],
                "subChecklists": []
              },
              {
                "name": "Eng lim/surge/stall R",
                "checks": [],
                "subChecklists": []
              },
              {
                "name": "Eng svr damage/sep L",
                "checks": [],
                "subChecklists": []
              },
              {
                "name": "Eng svr damage/sep R",
                "checks": [],
                "subChecklists": []
              }
            ]
          },
          {
            "name": "Fire, Smoke ...",
            "checks": [],
            "subChecklists": []
          },
          {
            "name": "Flight deck door, Windows ...",
            "checks": [],
            "subChecklists": []
          },
          {
            "name": "Airspeed unreliable",
            "checks": [],
            "subChecklists": []
          },
          {
            "name": "Ditching",
            "checks": [],
            "subChecklists": []
          },
          {
            "name": "Evacuation",
            "checks": [],
            "subChecklists": []
          },
          {
            "name": "Fuel jettison",
            "checks": [],
            "subChecklists": []
          },
          {
            "name": "Fuel leak",
            "checks": [],
            "subChecklists": []
          },
          {
            "name": "Gear lever locked on",
            "checks": [],
            "subChecklists": []
          },
          {
            "name": "Ice crystal icing",
            "checks": [],
            "subChecklists": []
          },
          {
            "name": "Jammed flight controls",
            "checks": [],
            "subChecklists": []
          },
          {
            "name": "Overweight landing",
            "checks": [],
            "subChecklists": []
          },
          {
            "name": "Tail strinke",
            "checks": [],
            "subChecklists": []
          },
          {
            "name": "Volcanic Ash",
            "checks": [],
            "subChecklists": []
          }
        ]
      },
      {
        "name": "Apln genl, emer eqpt, doors, windows",
        "checks": [
          {
            "name": "",
            "expectedValue": "",
            "isAutomatic": false
          }
        ]
      },
      {
        "name": "Air systems",
        "checks": [
          {
            "name": "",
            "expectedValue": "",
            "isAutomatic": false
          }
        ]
      },
      {
        "name": "Anti-ice, rain",
        "checks": [
          {
            "name": "",
            "expectedValue": "",
            "isAutomatic": false
          }
        ]
      },
      {
        "name": "Automatic flight",
        "checks": [
          {
            "name": "",
            "expectedValue": "",
            "isAutomatic": false
          }
        ]
      },
      {
        "name": "Communications datalink",
        "checks": [
          {
            "name": "",
            "expectedValue": "",
            "isAutomatic": false
          }
        ]
      },
      {
        "name": "Electrical",
        "checks": [
          {
            "name": "",
            "expectedValue": "",
            "isAutomatic": false
          }
        ]
      },
      {
        "name": "Engines, APU",
        "checks": [
          {
            "name": "",
            "expectedValue": "",
            "isAutomatic": false
          }
        ]
      },
      {
        "name": "Fire protection",
        "checks": [
          {
            "name": "",
            "expectedValue": "",
            "isAutomatic": false
          }
        ]
      },
      {
        "name": "Flight controls",
        "checks": [
          {
            "name": "",
            "expectedValue": "",
            "isAutomatic": false
          }
        ]
      },
      {
        "name": "Flight instruments, displays",
        "checks": [
          {
            "name": "",
            "expectedValue": "",
            "isAutomatic": false
          }
        ]
      },
      {
        "name": "Flight management, navigation",
        "checks": [
          {
            "name": "",
            "expectedValue": "",
            "isAutomatic": false
          }
        ]
      },
      {
        "name": "Fuel",
        "checks": [
          {
            "name": "",
            "expectedValue": "",
            "isAutomatic": false
          }
        ]
      },
      {
        "name": "Hydraulics, RAT",
        "checks": [
          {
            "name": "",
            "expectedValue": "",
            "isAutomatic": false
          }
        ]
      },
      {
        "name": "Landing gear",
        "checks": [
          {
            "name": "",
            "expectedValue": "",
            "isAutomatic": false
          }
        ]
      },
      {
        "name": "Warning systems, tail strike",
        "checks": [
          {
            "name": "",
            "expectedValue": "",
            "isAutomatic": false
          }
        ]
      }
    ]
  }
]